tour_guide/__init__.py
tour_guide/anchor_feature_names.py
tour_guide/anchor_features.py
tour_guide/anchors.py
tour_guide/apps.py
tour_guide/blocks.py
tour_guide/categories.py
tour_guide/decorators.py
tour_guide/links.py
tour_guide/middleware.py
tour_guide/mixins.py
tour_guide/model_fields.py
tour_guide/model_porter.py
tour_guide/models.py
tour_guide/navigation.py
tour_guide/permissions.py
tour_guide/query.py
tour_guide/utilities.py
tour_guide/validators.py
tour_guide/wagtail_hooks.py
tour_guide/migrations/0001_initial.py
tour_guide/migrations/0002_add_anchor_category_settings.py
tour_guide/migrations/__init__.py
tour_guide/static/tour_guide/css/breadcrumbs.css
tour_guide/static/tour_guide/css/breadcrumbs_style.css
tour_guide/static/tour_guide/css/dropdown.css
tour_guide/static/tour_guide/css/dropdown_style.css
tour_guide/static/tour_guide/css/site_map.css
tour_guide/static/tour_guide/css/site_map_style.css
tour_guide/static/tour_guide/css/tour_guide.css
tour_guide/static/tour_guide/css/tour_guide_extra.css
tour_guide/static/tour_guide/js/pointer-navigation.js
tour_guide/static/tour_guide/js/tour_guide.js
tour_guide/templates/tour_guide/blocks/navigation_block.html
tour_guide/templates/tour_guide/blocks/rich_link_block.html
tour_guide/templates/tour_guide/blocks/breadcrumbs/navigation_choices.html
tour_guide/templates/tour_guide/blocks/breadcrumbs/navigation_container.html
tour_guide/templates/tour_guide/blocks/breadcrumbs/navigation_option.html
tour_guide/templates/tour_guide/blocks/breadcrumbs/navigation_wrapper.html
tour_guide/templates/tour_guide/blocks/dropdown/navigation_choices.html
tour_guide/templates/tour_guide/blocks/dropdown/navigation_container.html
tour_guide/templates/tour_guide/blocks/dropdown/navigation_option.html
tour_guide/templates/tour_guide/blocks/dropdown/navigation_wrapper.html
tour_guide/templates/tour_guide/blocks/site_map/navigation_choices.html
tour_guide/templates/tour_guide/blocks/site_map/navigation_container.html
tour_guide-4.1.1.dist-info/AUTHORS.txt
tour_guide-4.1.1.dist-info/LICENSE.txt
tour_guide-4.1.1.dist-info/METADATA
tour_guide-4.1.1.dist-info/WHEEL
tour_guide-4.1.1.dist-info/top_level.txt
tour_guide-4.1.1.dist-info/zip-safe
tour_guide-4.1.1.dist-info/RECORD
