Metadata-Version: 2.1
Name: tour-guide
Version: 4.1.1
Summary: A Wagtail app for navigation components.
Home-page: https://github.com/high-dimensional/tour-guide
Author: High Dimensional Neurology Group, UCL
Author-email: pypi@highdimensional.net
License: BSD-3-Clause
Platform: any
Classifier: Framework :: Django
Classifier: Framework :: Wagtail
Classifier: Programming Language :: Python :: 3
Classifier: Programming Language :: Python :: 3.8
Classifier: License :: OSI Approved :: BSD License
Classifier: Operating System :: OS Independent
Requires-Python: >=3.8
License-File: LICENSE.txt
License-File: AUTHORS.txt
Requires-Dist: Django (<4.2,>=4.1)
Requires-Dist: wagtail (<4.2,>=4.1)
Requires-Dist: django-auxiliaries (<4.2,>=4.1)
Requires-Dist: model-porter (<4.2,>=4.1)
Requires-Dist: draftail-helpers (<4.2,>=4.1)
Requires-Dist: js-initiator (<4.2,>=4.1)
Requires-Dist: adede (<4.2,>=4.1)
Requires-Dist: wagtail-block-model-field (<4.2,>=4.1)
Requires-Dist: wagtail-dynamic-choice (<4.2,>=4.1)
Requires-Dist: wagtail-richer-text (<4.2,>=4.1)
Requires-Dist: wagtail-preference-blocks (<4.2,>=4.1)
Requires-Dist: media-catalogue (<4.2,>=4.1.2)
